tdb/__init__.py
tdb/dev.py
tdb/tdb.py
textdatabase-1.0.5.dist-info/LICENSE
textdatabase-1.0.5.dist-info/METADATA
textdatabase-1.0.5.dist-info/WHEEL
textdatabase-1.0.5.dist-info/top_level.txt
textdatabase-1.0.5.dist-info/RECORD
