Metadata-Version: 2.1
Name: textdatabase
Version: 1.0.5
Summary: A little text database for developers
Home-page: https://github.com/BinaryGuo/Bullet_Roulette
Author: GQX
Author-email: kill114514251@outlook.com
License: UNKNOWN
Platform: UNKNOWN
Classifier: Intended Audience :: Developers
Classifier: Development Status :: 5 - Production/Stable
Classifier: Natural Language :: English
Classifier: License :: OSI Approved :: MIT License
Classifier: Operating System :: POSIX :: Linux
Classifier: Operating System :: MacOS
Classifier: Operating System :: MacOS :: MacOS X
Classifier: Programming Language :: Python :: 3.13
Classifier: Programming Language :: Python :: 3.12
Classifier: Programming Language :: Python :: 3.11
Classifier: Programming Language :: Python :: 3.10
Classifier: Programming Language :: Python :: 3.9
Classifier: Programming Language :: Python :: 3.8
Classifier: Programming Language :: Python :: 3.7
Classifier: Programming Language :: Python :: 3.6
Classifier: Programming Language :: Python :: 3.5
Classifier: Programming Language :: Python :: 3.4
Classifier: Programming Language :: Python :: 3.3
Classifier: Programming Language :: Python :: 3.2
Classifier: Programming Language :: Python :: 3.1
Classifier: Programming Language :: Python :: 3
Requires-Python: >=3
License-File: LICENSE
Requires-Dist: pyotp (>=2.6.0)
